deletetweets/__init__.py
deletetweets/__main__.py
deletetweets/deletetweets.py
delete_tweets-2.0.1.dist-info/LICENSE
delete_tweets-2.0.1.dist-info/METADATA
delete_tweets-2.0.1.dist-info/WHEEL
delete_tweets-2.0.1.dist-info/entry_points.txt
delete_tweets-2.0.1.dist-info/top_level.txt
delete_tweets-2.0.1.dist-info/RECORD
