Metadata-Version: 2.1
Name: delete-tweets
Version: 2.0.1
Summary: Delete tweets from your Twitter timeline.
Home-page: https://github.com/koenrh/delete-tweets
Author: Koen Rouwhorst
Author-email: info@koenrouwhorst.nl
License: UNKNOWN
Platform: UNKNOWN
Classifier: Programming Language :: Python :: 3
Classifier: License :: OSI Approved :: ISC License (ISCL)
Classifier: Operating System :: OS Independent
Requires-Python: >=3
Requires-Dist: python-twitter (<4,>=3.5)
Requires-Dist: python-dateutil (<3,>=2.8.1)
